namedtupled/__init__.py
namedtupled/integrations.py
namedtupled/mapper.py
namedtupled/namedtupled.py
namedtupled-0.3.3.dist-info/DESCRIPTION.rst
namedtupled-0.3.3.dist-info/METADATA
namedtupled-0.3.3.dist-info/RECORD
namedtupled-0.3.3.dist-info/WHEEL
namedtupled-0.3.3.dist-info/metadata.json
namedtupled-0.3.3.dist-info/pbr.json
namedtupled-0.3.3.dist-info/top_level.txt
