Metadata-Version: 1.1
Name: namedtupled
Version: 0.3.3
Summary: Lightweight namedtuple wrapper for attribute-style data access (a la JavaScript objects).
Home-page: https://github.com/brennv/namedtupled
Author: brennv
Author-email: brennan@beta.build
License: MIT
Download-URL: https://github.com/brennv/namedtupled/tarball/0.3.3
Keywords: namedtupled namedtuple json yaml attribute style data access javascript objects
Platform: UNKNOWN
Classifier: Development Status :: 5 - Production/Stable
Classifier: Intended Audience :: Developers
Classifier: License :: OSI Approved :: MIT License
Classifier: Operating System :: OS Independent
Classifier: Programming Language :: Python
Classifier: Programming Language :: Python :: 2
Classifier: Programming Language :: Python :: 2.7
Classifier: Programming Language :: Python :: 3
Classifier: Programming Language :: Python :: 3.3
Classifier: Programming Language :: Python :: 3.4
Classifier: Programming Language :: Python :: 3.5
